toma/__init__.py
toma/batchsize_cache.py
toma/cpu_memory.py
toma/stacktrace.py
toma/torch_cuda_memory.py
toma-1.1.0.dist-info/LICENSE
toma-1.1.0.dist-info/METADATA
toma-1.1.0.dist-info/WHEEL
toma-1.1.0.dist-info/top_level.txt
toma-1.1.0.dist-info/RECORD
