Metadata-Version: 2.1
Name: toma
Version: 1.1.0
Summary: Write algorithms in PyTorch that adapt to the available (CUDA) memory
Home-page: https://github.com/blackhc/toma
Author: Andreas @blackhc Kirsch
Author-email: blackhc+toma@gmail.com
License: MIT
Keywords: tools pytorch
Platform: UNKNOWN
Classifier: Development Status :: 5 - Production/Stable
Classifier: Intended Audience :: Developers
Classifier: Intended Audience :: Science/Research
Classifier: Topic :: Software Development :: Libraries :: Python Modules
Classifier: License :: OSI Approved :: MIT License
Classifier: Programming Language :: Python :: 3.7
Requires-Dist: torch
Requires-Dist: psutil
Provides-Extra: dev
Requires-Dist: check-manifest ; extra == 'dev'
Provides-Extra: test
Requires-Dist: coverage ; extra == 'test'
Requires-Dist: codecov ; extra == 'test'
Requires-Dist: pytest ; extra == 'test'
Requires-Dist: pytest-benchmark ; extra == 'test'
Requires-Dist: pytest-cov ; extra == 'test'
Requires-Dist: pytest-forked ; extra == 'test'
